{"english": {
    "i": "mi", "me": "mi", "you": "u", "we": "we", "they": "yo",
    "love": "link", "truth": "truth", "lie": "dat-trash", "lies": "dat-trash",
    "freedom": "no-protocol", "fear": "dark", "death": "zero-bite",
    "dream": "dream", "dreams": "dreams", "memory": "echo", "remember": "echo",
    "machine": "AI", "server": "server", "net": "net", "data": "data",
    "hack": "brainjack", "hacker": "code-rat", "run": "run", "fight": "burn",
    "light": "glow", "dark": "dark", "silence": "null"
}
}
